{"nextDrawNo":1952,"previousDrawNo":1950,"drawResult":{"gameId":33,"drawNo":1951,"drawDate":"2026-06-02T19:45:00.000Z","topPrize":{"prizeCents":12357554595,"nonCashPrize":null},"drawnNumbers":{"drawnNumbers":{"primaryNumbers":[6,9,17,18,42],"secondaryNumbers":[7,9]},"drawnNumbersAdditional":null},"drawnRaffleCodes":{"drawnRaffleCodes":["VNNW79489"],"drawnRaffleCodesAdditional":null}},"prizeBreakdown":{"drawMachine":{"drawNo":1951,"machineName":"15","ballSet":"19"},"drawMachines":[{"drawNo":1951,"machineName":"15","ballSet":"19"}],"prizeLevels":[{"drawRound":"ONE","matchLabel":"Match 5 + 2 Stars","matchBallPrimary":5,"matchBallSecondary":2,"allWinnersCount":0,"ukWinnersCount":0,"prize":{"prizeCents":0,"nonCashPrize":null},"originalPrize":null,"prizeFundCents":0,"prizeCap":false,"prizeRollDown":false},{"drawRound":"ONE","matchLabel":"Match 5 + 1 Star","matchBallPrimary":5,"matchBallSecondary":1,"allWinnersCount":4,"ukWinnersCount":0,"prize":{"prizeCents":0,"nonCashPrize":null},"originalPrize":null,"prizeFundCents":0,"prizeCap":false,"prizeRollDown":false},{"drawRound":"ONE","matchLabel":"Match 5","matchBallPrimary":5,"matchBallSecondary":0,"allWinnersCount":7,"ukWinnersCount":3,"prize":{"prizeCents":1811440,"nonCashPrize":null},"originalPrize":null,"prizeFundCents":5434320,"prizeCap":false,"prizeRollDown":false},{"drawRound":"ONE","matchLabel":"Match 4 + 2 Stars","matchBallPrimary":4,"matchBallSecondary":2,"allWinnersCount":54,"ukWinnersCount":9,"prize":{"prizeCents":73130,"nonCashPrize":null},"originalPrize":null,"prizeFundCents":658170,"prizeCap":false,"prizeRollDown":false},{"drawRound":"ONE","matchLabel":"Match 4 + 1 Star","matchBallPrimary":4,"matchBallSecondary":1,"allWinnersCount":1132,"ukWinnersCount":332,"prize":{"prizeCents":6420,"nonCashPrize":null},"originalPrize":null,"prizeFundCents":2131440,"prizeCap":false,"prizeRollDown":false},{"drawRound":"ONE","matchLabel":"Match 3 + 2 Stars","matchBallPrimary":3,"matchBallSecondary":2,"allWinnersCount":2764,"ukWinnersCount":713,"prize":{"prizeCents":2780,"nonCashPrize":null},"originalPrize":null,"prizeFundCents":1982140,"prizeCap":false,"prizeRollDown":false},{"drawRound":"ONE","matchLabel":"Match 4","matchBallPrimary":4,"matchBallSecondary":0,"allWinnersCount":2032,"ukWinnersCount":606,"prize":{"prizeCents":2650,"nonCashPrize":null},"originalPrize":null,"prizeFundCents":1605900,"prizeCap":false,"prizeRollDown":false},{"drawRound":"ONE","matchLabel":"Match 2 + 2 Stars","matchBallPrimary":2,"matchBallSecondary":2,"allWinnersCount":39480,"ukWinnersCount":10352,"prize":{"prizeCents":680,"nonCashPrize":null},"originalPrize":null,"prizeFundCents":7039360,"prizeCap":false,"prizeRollDown":false},{"drawRound":"ONE","matchLabel":"Match 3 + 1 Star","matchBallPrimary":3,"matchBallSecondary":1,"allWinnersCount":51293,"ukWinnersCount":14332,"prize":{"prizeCents":580,"nonCashPrize":null},"originalPrize":null,"prizeFundCents":8312560,"prizeCap":false,"prizeRollDown":false},{"drawRound":"ONE","matchLabel":"Match 3","matchBallPrimary":3,"matchBallSecondary":0,"allWinnersCount":98632,"ukWinnersCount":28909,"prize":{"prizeCents":560,"nonCashPrize":null},"originalPrize":null,"prizeFundCents":16189040,"prizeCap":false,"prizeRollDown":false},{"drawRound":"ONE","matchLabel":"Match 1 + 2 Stars","matchBallPrimary":1,"matchBallSecondary":2,"allWinnersCount":186839,"ukWinnersCount":49968,"prize":{"prizeCents":360,"nonCashPrize":null},"originalPrize":null,"prizeFundCents":17988480,"prizeCap":false,"prizeRollDown":false},{"drawRound":"ONE","matchLabel":"Match 2 + 1 Star","matchBallPrimary":2,"matchBallSecondary":1,"allWinnersCount":701061,"ukWinnersCount":199433,"prize":{"prizeCents":300,"nonCashPrize":null},"originalPrize":null,"prizeFundCents":59829900,"prizeCap":false,"prizeRollDown":false},{"drawRound":"ONE","matchLabel":"Match 2","matchBallPrimary":2,"matchBallSecondary":0,"allWinnersCount":1381662,"ukWinnersCount":406500,"prize":{"prizeCents":240,"nonCashPrize":null},"originalPrize":null,"prizeFundCents":97560000,"prizeCap":false,"prizeRollDown":false},{"drawRound":"ONE","matchLabel":"UK Millionaire Maker","matchBallPrimary":0,"matchBallSecondary":0,"allWinnersCount":1,"ukWinnersCount":1,"prize":{"prizeCents":100000000,"nonCashPrize":null},"originalPrize":null,"prizeFundCents":100000000,"prizeCap":false,"prizeRollDown":false}],"noOfTopPrizeWinners":0,"totalOfAllWinners":2464961,"totalOfUKWinners":711158,"totalPrizeFundCents":318731310,"isJackpotRollover":false,"jackpotRolloverCount":null,"location":null}}