{"nextDrawNo":728,"previousDrawNo":726,"drawResult":{"gameId":3,"drawNo":727,"drawDate":"2026-03-02T20:00:00.000Z","topPrize":{"prizeCents":null,"nonCashPrize":"£10,000 every month for 30 years"},"drawnNumbers":{"drawnNumbers":{"primaryNumbers":[2,13,22,29,31],"secondaryNumbers":[3]},"drawnNumbersAdditional":null},"drawnRaffleCodes":null},"prizeBreakdown":{"drawMachine":{"drawNo":727,"machineName":"Excalibur4","ballSet":"SFL5"},"drawMachines":[{"drawNo":727,"machineName":"Excalibur4","ballSet":"SFL5"}],"prizeLevels":[{"drawRound":"ONE","matchLabel":"Match 5 + Life Ball","matchBallPrimary":5,"matchBallSecondary":1,"allWinnersCount":0,"ukWinnersCount":null,"prize":{"prizeCents":0,"nonCashPrize":null},"originalPrize":null,"prizeFundCents":0,"prizeCap":false,"prizeRollDown":false},{"drawRound":"ONE","matchLabel":"Match 5","matchBallPrimary":5,"matchBallSecondary":0,"allWinnersCount":3,"ukWinnersCount":null,"prize":{"prizeCents":null,"nonCashPrize":"£10,000 every month for one year"},"originalPrize":null,"prizeFundCents":36000000,"prizeCap":false,"prizeRollDown":false},{"drawRound":"ONE","matchLabel":"Match 4 + Life Ball","matchBallPrimary":4,"matchBallSecondary":1,"allWinnersCount":35,"ukWinnersCount":null,"prize":{"prizeCents":25000,"nonCashPrize":null},"originalPrize":null,"prizeFundCents":875000,"prizeCap":false,"prizeRollDown":false},{"drawRound":"ONE","matchLabel":"Match 4","matchBallPrimary":4,"matchBallSecondary":0,"allWinnersCount":289,"ukWinnersCount":null,"prize":{"prizeCents":5000,"nonCashPrize":null},"originalPrize":null,"prizeFundCents":1445000,"prizeCap":false,"prizeRollDown":false},{"drawRound":"ONE","matchLabel":"Match 3 + Life Ball","matchBallPrimary":3,"matchBallSecondary":1,"allWinnersCount":1346,"ukWinnersCount":null,"prize":{"prizeCents":3000,"nonCashPrize":null},"originalPrize":null,"prizeFundCents":4038000,"prizeCap":false,"prizeRollDown":false},{"drawRound":"ONE","matchLabel":"Match 3","matchBallPrimary":3,"matchBallSecondary":0,"allWinnersCount":12002,"ukWinnersCount":null,"prize":{"prizeCents":2000,"nonCashPrize":null},"originalPrize":null,"prizeFundCents":24004000,"prizeCap":false,"prizeRollDown":false},{"drawRound":"ONE","matchLabel":"Match 2 + Life Ball","matchBallPrimary":2,"matchBallSecondary":1,"allWinnersCount":17320,"ukWinnersCount":null,"prize":{"prizeCents":1000,"nonCashPrize":null},"originalPrize":null,"prizeFundCents":17320000,"prizeCap":false,"prizeRollDown":false},{"drawRound":"ONE","matchLabel":"Match 2","matchBallPrimary":2,"matchBallSecondary":0,"allWinnersCount":147376,"ukWinnersCount":null,"prize":{"prizeCents":500,"nonCashPrize":null},"originalPrize":null,"prizeFundCents":73688000,"prizeCap":false,"prizeRollDown":false}],"noOfTopPrizeWinners":0,"totalOfAllWinners":178371,"totalOfUKWinners":null,"totalPrizeFundCents":157370000,"isJackpotRollover":false,"jackpotRolloverCount":null,"location":null}}